dbjson/__init__.py
DBJSONS-1.0.2.dist-info/LICENSE.txt
DBJSONS-1.0.2.dist-info/METADATA
DBJSONS-1.0.2.dist-info/WHEEL
DBJSONS-1.0.2.dist-info/top_level.txt
DBJSONS-1.0.2.dist-info/RECORD
