Metadata-Version: 2.1
Name: DBJSONS
Version: 1.0.2
Summary: dbjson is a module that can help you use json as database
Home-page: https://github.com/IM-code111/dbjson-1.0.1
Author: Afiq
Author-email: muhammad184276@gmail.com
License: UNKNOWN
Platform: UNKNOWN
Classifier: Programming Language :: Python :: 3
Classifier: License :: OSI Approved :: MIT License
Classifier: Operating System :: OS Independent
Requires-Python: >=3.6
